compynent/__init__.py
compynent/_impl.py
compynent-1.0.1.dist-info/LICENSE
compynent-1.0.1.dist-info/METADATA
compynent-1.0.1.dist-info/WHEEL
compynent-1.0.1.dist-info/top_level.txt
compynent-1.0.1.dist-info/RECORD
