Metadata-Version: 2.1
Name: compynent
Version: 1.0.1
Summary: Components in Python
Home-page: https://github.com/caioaao/compynent
Author: Caio Oliveira
Author-email: caioaao@gmail.com
License: MIT license
Keywords: compynent
Platform: UNKNOWN
Classifier: Intended Audience :: Developers
Classifier: License :: OSI Approved :: MIT License
Classifier: Natural Language :: English
Classifier: Programming Language :: Python :: 3.7
Classifier: Programming Language :: Python :: 3.8
Requires-Python: >=3.5
